asciify/__init__.py
asciify/asciify.py
asciify/letter_profiles.py
asciify/word_creator.py
asciify/word_renderer.py
asciify-0.0.5.dist-info/DESCRIPTION.rst
asciify-0.0.5.dist-info/METADATA
asciify-0.0.5.dist-info/RECORD
asciify-0.0.5.dist-info/WHEEL
asciify-0.0.5.dist-info/entry_points.txt
asciify-0.0.5.dist-info/metadata.json
asciify-0.0.5.dist-info/top_level.txt
