Metadata-Version: 2.0
Name: asciify
Version: 0.0.5
Summary: Fun little project
Home-page: https://github.com/paolopaolopaolo/ascii_text_generator/
Author: Dean Mercado
Author-email: dpaolomercado@gmail.com
License: GNU
Platform: UNKNOWN
Classifier: Development Status :: 3 - Alpha
Requires-Dist: click (==6.6)
